RandAlgo/Trail_Vail.py
RandAlgo/greet.py
Tri_Vail-1.0.0.dist-info/LICENSE
Tri_Vail-1.0.0.dist-info/METADATA
Tri_Vail-1.0.0.dist-info/WHEEL
Tri_Vail-1.0.0.dist-info/entry_points.txt
Tri_Vail-1.0.0.dist-info/top_level.txt
Tri_Vail-1.0.0.dist-info/RECORD
